edinet/__init__.py
edinet/main.py
edinet/enums/__init__.py
edinet/enums/exceptions.py
edinet/enums/response.py
edinet_wrap-0.13.dist-info/LICENSE
edinet_wrap-0.13.dist-info/METADATA
edinet_wrap-0.13.dist-info/WHEEL
edinet_wrap-0.13.dist-info/top_level.txt
edinet_wrap-0.13.dist-info/RECORD
