Metadata-Version: 2.1
Name: edinet-wrap
Version: 0.13
Summary: EDINET API wrapper.
Author: iodine53
Maintainer: iodine53
License: Apache Software License
Project-URL: Repository, https://github.com/35enidoi/edinet_wrap
Project-URL: Issues, https://github.com/35enidoi/edinet_wrap/issues
Keywords: edinet
Classifier: Development Status :: 4 - Beta
Classifier: License :: OSI Approved :: Apache Software License
Classifier: Programming Language :: Python :: 3.9
Classifier: Programming Language :: Python :: 3.10
Classifier: Programming Language :: Python :: 3.11
Classifier: Programming Language :: Python :: 3.12
Requires-Python: >=3.9
License-File: LICENSE
Requires-Dist: requests
